.gitignore
CHANGELOG.md
LICENSE
Makefile
README.md
requirements-dev.txt
setup.cfg
setup.py
.github/workflows/ci.yml
demos/benchmark.py
demos/compare.py
demos/competitors.py
libversion/__init__.py
libversion/_libversion.pyi
libversion/py.typed
libversion.egg-info/PKG-INFO
libversion.egg-info/SOURCES.txt
libversion.egg-info/dependency_links.txt
libversion.egg-info/top_level.txt
src/_libversion.c
tests/__init__.py
tests/test_cversion.py
tests/test_pyversion.py